{
    "method": "single_train",
    "run_id": "single_train_194111",
    "macro_avg": {},
    "best_epoch": 18,
    "best_valid_metric_value": 1.6031025419048235,
    "valid_metric_name": "valid_loss",
    "train_loss_at_best": 1.7117643930380766,
    "train_acc_at_best": 0.5277914412198721,
    "valid_acc_at_best": 0.5333333333333333,
    "saved_model_path": null,
    "full_params_used": {
        "module": null,
        "criterion": null,
        "optimizer": null,
        "lr": 5e-05,
        "max_epochs": 60,
        "batch_size": 32,
        "device": "cuda",
        "callbacks": [
            [
                "progress_bar",
                "ProgressBar"
            ],
            [
                "default_early_stopping",
                "EarlyStopping"
            ],
            [
                "default_lr_scheduler",
                "LRScheduler"
            ],
            [
                "default_train_acc_scorer",
                "EpochScoring"
            ],
            [
                "file_log_table_cb",
                "FileLogTable"
            ]
        ],
        "train_transform": null,
        "valid_transform": null,
        "show_first_batch_augmentation": true,
        "use_offline_augmented_data": false,
        "dataset_handler_ref": "<server.ml.dataset_utils.ImageDatasetHandler object at 0x0000014BB3085350>",
        "classes": [
            0,
            1,
            2,
            3,
            4,
            5,
            6,
            7,
            8,
            9,
            10
        ],
        "verbose": 0,
        "module__num_classes": 11,
        "optimizer__weight_decay": 0.1,
        "callbacks__default_early_stopping__patience": 15,
        "criterion__label_smoothing": 0.1,
        "cutmix_alpha": 1.0,
        "cutmix_probability": 0.9,
        "gradient_clip_value": 5.0,
        "module__cnn_extractor_type": "standard_cnn",
        "module__cnn_model_name": "efficientnet_b0",
        "module__cnn_pretrained_imagenet": true,
        "module__cnn_output_channels_target": 192,
        "module__cnn_freeze_extractor": false,
        "module__cnn_num_frozen_stages": 2,
        "module__cnn_fine_tuned_weights_path": null,
        "module__vit_model_variant": "vit_b_16",
        "module__vit_pretrained_imagenet": true,
        "module__unfreeze_strategy": "encoder_tail",
        "module__num_transformer_blocks_to_unfreeze": 2,
        "module__unfreeze_cls_token": true,
        "module__unfreeze_pos_embedding": true,
        "module__unfreeze_patch_embedding": false,
        "module__unfreeze_encoder_layernorm": true,
        "module__custom_head_hidden_dims": null,
        "module__head_dropout_rate": 0.2,
        "module__pipeline_img_h": 224,
        "module__pipeline_img_w": 224,
        "iterator_train__shuffle": true,
        "train_split": null
    },
    "training_history": [
        {
            "epoch": 1,
            "train_batch_count": 64,
            "valid_batch_count": 8,
            "dur": 18.013166189193726,
            "train_loss": 2.3560107730024855,
            "train_loss_best": true,
            "valid_loss": 2.1538920982211245,
            "valid_loss_best": true,
            "valid_acc": 0.28627450980392155,
            "valid_acc_best": true,
            "event_lr": 5e-05,
            "train_acc": 0.1662567634038367,
            "train_acc_best": true
        },
        {
            "epoch": 2,
            "train_batch_count": 64,
            "valid_batch_count": 8,
            "dur": 14.555123567581177,
            "train_loss": 2.1677004006831915,
            "train_loss_best": true,
            "valid_loss": 1.8623285644194658,
            "valid_loss_best": true,
            "valid_acc": 0.4196078431372549,
            "valid_acc_best": true,
            "event_lr": 4.996642360148706e-05,
            "train_acc": 0.2828332513526808,
            "train_acc_best": true
        },
        {
            "epoch": 3,
            "train_batch_count": 64,
            "valid_batch_count": 8,
            "dur": 14.282468557357788,
            "train_loss": 2.0601975875011056,
            "train_loss_best": true,
            "valid_loss": 1.7803612087287155,
            "valid_loss_best": true,
            "valid_acc": 0.45098039215686275,
            "valid_acc_best": true,
            "event_lr": 4.98657864365227e-05,
            "train_acc": 0.33497294638465325,
            "train_acc_best": true
        },
        {
            "epoch": 4,
            "train_batch_count": 64,
            "valid_batch_count": 8,
            "dur": 14.025821208953857,
            "train_loss": 1.9851991075983906,
            "train_loss_best": true,
            "valid_loss": 1.7226738074246575,
            "valid_loss_best": true,
            "valid_acc": 0.47843137254901963,
            "valid_acc_best": true,
            "event_lr": 4.9698364344580884e-05,
            "train_acc": 0.3782587309394983,
            "train_acc_best": true
        },
        {
            "epoch": 5,
            "train_batch_count": 64,
            "valid_batch_count": 8,
            "dur": 14.139168500900269,
            "train_loss": 1.9619239179946142,
            "train_loss_best": true,
            "valid_loss": 1.66734933385662,
            "valid_loss_best": true,
            "valid_acc": 0.48627450980392156,
            "valid_acc_best": true,
            "event_lr": 4.946461621797825e-05,
            "train_acc": 0.39055582882439743,
            "train_acc_best": true
        },
        {
            "epoch": 6,
            "train_batch_count": 64,
            "valid_batch_count": 8,
            "dur": 14.16633915901184,
            "train_loss": 1.9327318632596828,
            "train_loss_best": true,
            "valid_loss": 1.6574447814156028,
            "valid_loss_best": true,
            "valid_acc": 0.49411764705882355,
            "valid_acc_best": true,
            "event_lr": 4.916518274408218e-05,
            "train_acc": 0.39695031972454503,
            "train_acc_best": true
        },
        {
            "epoch": 7,
            "train_batch_count": 64,
            "valid_batch_count": 8,
            "dur": 13.997273445129395,
            "train_loss": 1.9045245232279524,
            "train_loss_best": true,
            "valid_loss": 1.6419729550679525,
            "valid_loss_best": true,
            "valid_acc": 0.5019607843137255,
            "valid_acc_best": true,
            "event_lr": 4.880088464923128e-05,
            "train_acc": 0.3939990162321692,
            "train_acc_best": false
        },
        {
            "epoch": 8,
            "train_batch_count": 64,
            "valid_batch_count": 8,
            "dur": 13.97178053855896,
            "train_loss": 1.902133022923805,
            "train_loss_best": true,
            "valid_loss": 1.6832659253887101,
            "valid_loss_best": false,
            "valid_acc": 0.48627450980392156,
            "valid_acc_best": false,
            "event_lr": 4.837272044918145e-05,
            "train_acc": 0.411706837186424,
            "train_acc_best": true
        },
        {
            "epoch": 9,
            "train_batch_count": 64,
            "valid_batch_count": 8,
            "dur": 13.957160711288452,
            "train_loss": 1.858324633639139,
            "train_loss_best": true,
            "valid_loss": 1.6189853317597334,
            "valid_loss_best": true,
            "valid_acc": 0.5098039215686274,
            "valid_acc_best": true,
            "event_lr": 4.7881863712243726e-05,
            "train_acc": 0.42400393507132317,
            "train_acc_best": true
        },
        {
            "epoch": 10,
            "train_batch_count": 64,
            "valid_batch_count": 8,
            "dur": 14.121229887008667,
            "train_loss": 1.878472718357512,
            "train_loss_best": false,
            "valid_loss": 1.63277642399657,
            "valid_loss_best": false,
            "valid_acc": 0.5098039215686274,
            "valid_acc_best": false,
            "event_lr": 4.7329659842615016e-05,
            "train_acc": 0.40924741760944416,
            "train_acc_best": false
        },
        {
            "epoch": 11,
            "train_batch_count": 64,
            "valid_batch_count": 8,
            "dur": 14.293879270553589,
            "train_loss": 1.8239579527939827,
            "train_loss_best": true,
            "valid_loss": 1.6483747687994266,
            "valid_loss_best": false,
            "valid_acc": 0.5137254901960784,
            "valid_acc_best": true,
            "event_lr": 4.671762239271876e-05,
            "train_acc": 0.4303984259714707,
            "train_acc_best": true
        },
        {
            "epoch": 12,
            "train_batch_count": 64,
            "valid_batch_count": 8,
            "dur": 14.298065423965454,
            "train_loss": 1.7789736060279961,
            "train_loss_best": true,
            "valid_loss": 1.6132337004530664,
            "valid_loss_best": true,
            "valid_acc": 0.5019607843137255,
            "valid_acc_best": false,
            "event_lr": 4.6047428914662896e-05,
            "train_acc": 0.47712739793408754,
            "train_acc_best": true
        },
        {
            "epoch": 13,
            "train_batch_count": 64,
            "valid_batch_count": 8,
            "dur": 14.016021966934204,
            "train_loss": 1.7520176473064957,
            "train_loss_best": true,
            "valid_loss": 1.6236026969610475,
            "valid_loss_best": false,
            "valid_acc": 0.4980392156862745,
            "valid_acc_best": false,
            "event_lr": 4.532091636218622e-05,
            "train_acc": 0.48352188883423514,
            "train_acc_best": true
        },
        {
            "epoch": 14,
            "train_batch_count": 64,
            "valid_batch_count": 8,
            "dur": 14.277835845947266,
            "train_loss": 1.7530455009373198,
            "train_loss_best": false,
            "valid_loss": 1.620422020145491,
            "valid_loss_best": false,
            "valid_acc": 0.5176470588235295,
            "valid_acc_best": true,
            "event_lr": 4.4540076055695796e-05,
            "train_acc": 0.5017215937038859,
            "train_acc_best": true
        },
        {
            "epoch": 15,
            "train_batch_count": 64,
            "valid_batch_count": 8,
            "dur": 14.411051750183105,
            "train_loss": 1.7390172991679915,
            "train_loss_best": true,
            "valid_loss": 1.6164434732175341,
            "valid_loss_best": false,
            "valid_acc": 0.5176470588235295,
            "valid_acc_best": false,
            "event_lr": 4.370704822419617e-05,
            "train_acc": 0.4963108706345303,
            "train_acc_best": false
        },
        {
            "epoch": 16,
            "train_batch_count": 64,
            "valid_batch_count": 8,
            "dur": 14.384294271469116,
            "train_loss": 1.6844194632003417,
            "train_loss_best": true,
            "valid_loss": 1.6278490440518247,
            "valid_loss_best": false,
            "valid_acc": 0.5215686274509804,
            "valid_acc_best": true,
            "event_lr": 4.282411613907043e-05,
            "train_acc": 0.5346778160354156,
            "train_acc_best": true
        },
        {
            "epoch": 17,
            "train_batch_count": 64,
            "valid_batch_count": 8,
            "dur": 14.350401401519775,
            "train_loss": 1.7059502867836114,
            "train_loss_best": false,
            "valid_loss": 1.6226319018532247,
            "valid_loss_best": false,
            "valid_acc": 0.5058823529411764,
            "valid_acc_best": false,
            "event_lr": 4.189369985579204e-05,
            "train_acc": 0.5174618789965568,
            "train_acc_best": false
        },
        {
            "epoch": 18,
            "train_batch_count": 64,
            "valid_batch_count": 8,
            "dur": 14.200071811676025,
            "train_loss": 1.7117643930380766,
            "train_loss_best": false,
            "valid_loss": 1.6031025419048235,
            "valid_loss_best": true,
            "valid_acc": 0.5333333333333333,
            "valid_acc_best": true,
            "event_lr": 4.091834958072103e-05,
            "train_acc": 0.5277914412198721,
            "train_acc_best": false
        },
        {
            "epoch": 19,
            "train_batch_count": 64,
            "valid_batch_count": 8,
            "dur": 14.326961040496826,
            "train_loss": 1.7426569493486561,
            "train_loss_best": false,
            "valid_loss": 1.6202322483062743,
            "valid_loss_best": false,
            "valid_acc": 0.5098039215686274,
            "valid_acc_best": false,
            "event_lr": 3.99007386811656e-05,
            "train_acc": 0.5174618789965568,
            "train_acc_best": false
        },
        {
            "epoch": 20,
            "train_batch_count": 64,
            "valid_batch_count": 8,
            "dur": 14.100775718688965,
            "train_loss": 1.623468670068676,
            "train_loss_best": true,
            "valid_loss": 1.623834516955357,
            "valid_loss_best": false,
            "valid_acc": 0.5137254901960784,
            "valid_acc_best": false,
            "event_lr": 3.884365635786817e-05,
            "train_acc": 0.5553369404820462,
            "train_acc_best": true
        },
        {
            "epoch": 21,
            "train_batch_count": 64,
            "valid_batch_count": 8,
            "dur": 14.210116386413574,
            "train_loss": 1.6152751437561066,
            "train_loss_best": true,
            "valid_loss": 1.6326076357972388,
            "valid_loss_best": false,
            "valid_acc": 0.49411764705882355,
            "valid_acc_best": false,
            "event_lr": 3.775e-05,
            "train_acc": 0.5425479586817511,
            "train_acc_best": false
        },
        {
            "epoch": 22,
            "train_batch_count": 64,
            "valid_batch_count": 8,
            "dur": 14.201406955718994,
            "train_loss": 1.6218838337543149,
            "train_loss_best": false,
            "valid_loss": 1.6339495630825267,
            "valid_loss_best": false,
            "valid_acc": 0.5019607843137255,
            "valid_acc_best": false,
            "event_lr": 3.66227672436189e-05,
            "train_acc": 0.5017215937038859,
            "train_acc_best": false
        },
        {
            "epoch": 23,
            "train_batch_count": 64,
            "valid_batch_count": 8,
            "dur": 14.22654414176941,
            "train_loss": 1.6529092107332815,
            "train_loss_best": false,
            "valid_loss": 1.622339115890802,
            "valid_loss_best": false,
            "valid_acc": 0.5254901960784314,
            "valid_acc_best": false,
            "event_lr": 3.5465047755357117e-05,
            "train_acc": 0.5573044761436301,
            "train_acc_best": true
        },
        {
            "epoch": 24,
            "train_batch_count": 64,
            "valid_batch_count": 8,
            "dur": 14.108570337295532,
            "train_loss": 1.6234367269045955,
            "train_loss_best": false,
            "valid_loss": 1.6448962258357627,
            "valid_loss_best": false,
            "valid_acc": 0.5411764705882353,
            "valid_acc_best": true,
            "event_lr": 3.428001476385987e-05,
            "train_acc": 0.5209050664043285,
            "train_acc_best": false
        },
        {
            "epoch": 25,
            "train_batch_count": 64,
            "valid_batch_count": 8,
            "dur": 14.181239366531372,
            "train_loss": 1.590187914724486,
            "train_loss_best": true,
            "valid_loss": 1.6390867476369821,
            "valid_loss_best": false,
            "valid_acc": 0.5019607843137255,
            "valid_acc_best": false,
            "event_lr": 3.307091636218622e-05,
            "train_acc": 0.6045253320216429,
            "train_acc_best": true
        },
        {
            "epoch": 26,
            "train_batch_count": 64,
            "valid_batch_count": 8,
            "dur": 14.09632420539856,
            "train_loss": 1.6041916899064228,
            "train_loss_best": false,
            "valid_loss": 1.6192725111456479,
            "valid_loss_best": false,
            "valid_acc": 0.5450980392156862,
            "valid_acc_best": true,
            "event_lr": 3.1841066605011764e-05,
            "train_acc": 0.5774717166748647,
            "train_acc_best": false
        },
        {
            "epoch": 27,
            "train_batch_count": 64,
            "valid_batch_count": 8,
            "dur": 14.385563373565674,
            "train_loss": 1.5804062579221112,
            "train_loss_best": true,
            "valid_loss": 1.6418824251960307,
            "valid_loss_best": false,
            "valid_acc": 0.5411764705882353,
            "valid_acc_best": false,
            "event_lr": 3.0593836425035106e-05,
            "train_acc": 0.6060009837678307,
            "train_acc_best": true
        },
        {
            "epoch": 28,
            "train_batch_count": 64,
            "valid_batch_count": 8,
            "dur": 14.367318868637085,
            "train_loss": 1.5176266853409452,
            "train_loss_best": true,
            "valid_loss": 1.6491021843517528,
            "valid_loss_best": false,
            "valid_acc": 0.5215686274509804,
            "valid_acc_best": false,
            "event_lr": 2.9332644393485664e-05,
            "train_acc": 0.602557796360059,
            "train_acc_best": false
        },
        {
            "epoch": 29,
            "train_batch_count": 64,
            "valid_batch_count": 8,
            "dur": 14.177596092224121,
            "train_loss": 1.6027016552340145,
            "train_loss_best": false,
            "valid_loss": 1.6502903237062343,
            "valid_loss_best": false,
            "valid_acc": 0.5372549019607843,
            "valid_acc_best": false,
            "event_lr": 2.8060947350057517e-05,
            "train_acc": 0.5528775209050664,
            "train_acc_best": false
        },
        {
            "epoch": 30,
            "train_batch_count": 64,
            "valid_batch_count": 8,
            "dur": 14.034775733947754,
            "train_loss": 1.5098636642325645,
            "train_loss_best": true,
            "valid_loss": 1.6338593062232523,
            "valid_loss_best": false,
            "valid_acc": 0.5254901960784314,
            "valid_acc_best": false,
            "event_lr": 2.6782230927952127e-05,
            "train_acc": 0.6556812592228234,
            "train_acc_best": true
        },
        {
            "epoch": 31,
            "train_batch_count": 64,
            "valid_batch_count": 8,
            "dur": 14.162843227386475,
            "train_loss": 1.491042716832684,
            "train_loss_best": true,
            "valid_loss": 1.6736233084809546,
            "valid_loss_best": false,
            "valid_acc": 0.5294117647058824,
            "valid_acc_best": false,
            "event_lr": 2.5500000000000013e-05,
            "train_acc": 0.5745204131824889,
            "train_acc_best": false
        },
        {
            "epoch": 32,
            "train_batch_count": 64,
            "valid_batch_count": 8,
            "dur": 14.065719366073608,
            "train_loss": 1.5318143589415694,
            "train_loss_best": false,
            "valid_loss": 1.6866096809798596,
            "valid_loss_best": false,
            "valid_acc": 0.5254901960784314,
            "valid_acc_best": false,
            "event_lr": 2.421776907204789e-05,
            "train_acc": 0.58780127889818,
            "train_acc_best": false
        },
        {
            "epoch": 33,
            "train_batch_count": 64,
            "valid_batch_count": 8,
            "dur": 14.270451545715332,
            "train_loss": 1.478479099695869,
            "train_loss_best": true,
            "valid_loss": 1.69574482347451,
            "valid_loss_best": false,
            "valid_acc": 0.5215686274509804,
            "valid_acc_best": false
        }
    ]
}