{
    "method": "single_train",
    "run_id": "single_train_144029",
    "macro_avg": {},
    "best_epoch": 1,
    "best_valid_metric_value": NaN,
    "valid_metric_name": "valid_loss",
    "train_loss_at_best": NaN,
    "train_acc_at_best": NaN,
    "valid_acc_at_best": NaN,
    "saved_model_path": null,
    "full_params_used": {
        "module": null,
        "criterion": null,
        "optimizer": null,
        "lr": 5e-05,
        "max_epochs": 70,
        "batch_size": 16,
        "device": "cuda",
        "callbacks": [
            [
                "progress_bar",
                "ProgressBar"
            ],
            [
                "default_early_stopping",
                "EarlyStopping"
            ],
            [
                "default_lr_scheduler",
                "LRScheduler"
            ],
            [
                "default_train_acc_scorer",
                "EpochScoring"
            ],
            [
                "file_log_table_cb",
                "FileLogTable"
            ]
        ],
        "train_transform": null,
        "valid_transform": null,
        "show_first_batch_augmentation": true,
        "use_offline_augmented_data": true,
        "dataset_handler_ref": "<server.ml.dataset_utils.ImageDatasetHandler object at 0x000001BEA7C05D50>",
        "classes": [
            0,
            1,
            2,
            3,
            4,
            5,
            6,
            7,
            8,
            9,
            10
        ],
        "verbose": 0,
        "module__num_classes": 11,
        "optimizer__weight_decay": 0.2,
        "callbacks__default_early_stopping__patience": 15,
        "cutmix_alpha": 1.0,
        "cutmix_probability": 0.9,
        "module__vit_model_variant": "vit_b_16",
        "module__pretrained": true,
        "module__unfreeze_strategy": "encoder_tail",
        "module__num_transformer_blocks_to_unfreeze": 1,
        "module__unfreeze_cls_token": true,
        "module__unfreeze_pos_embedding": true,
        "module__unfreeze_patch_embedding": false,
        "module__unfreeze_encoder_layernorm": true,
        "module__custom_head_hidden_dims": null,
        "module__head_dropout_rate": 0.5,
        "train_split": null
    },
    "training_history": [
        {
            "epoch": 1
        }
    ]
}