{
    "method": "single_train",
    "run_id": "single_train_190335",
    "macro_avg": {},
    "best_epoch": 18,
    "best_valid_metric_value": 1.4881882222337277,
    "valid_metric_name": "valid_loss",
    "train_loss_at_best": 0.9778760733161884,
    "train_acc_at_best": 0.6803933620159803,
    "valid_acc_at_best": 0.4864864864864865,
    "saved_model_path": null,
    "full_params_used": {
        "module": null,
        "criterion": null,
        "optimizer": null,
        "lr": 1e-05,
        "max_epochs": 70,
        "batch_size": 16,
        "device": "cuda",
        "callbacks": [
            [
                "progress_bar",
                "ProgressBar"
            ],
            [
                "default_early_stopping",
                "EarlyStopping"
            ],
            [
                "default_lr_scheduler",
                "LRScheduler"
            ],
            [
                "default_train_acc_scorer",
                "EpochScoring"
            ],
            [
                "file_log_table_cb",
                "FileLogTable"
            ]
        ],
        "train_transform": null,
        "valid_transform": null,
        "show_first_batch_augmentation": true,
        "classes": [
            0,
            1,
            2,
            3,
            4,
            5,
            6,
            7,
            8,
            9,
            10
        ],
        "verbose": 0,
        "module__num_classes": 11,
        "optimizer__weight_decay": 0.05,
        "module__vit_model_variant": "vit_b_16",
        "module__pretrained": true,
        "module__unfreeze_strategy": "encoder_tail",
        "module__num_transformer_blocks_to_unfreeze": 2,
        "module__unfreeze_cls_token": true,
        "module__unfreeze_pos_embedding": true,
        "module__unfreeze_patch_embedding": false,
        "module__unfreeze_encoder_layernorm": true,
        "module__custom_head_hidden_dims": null,
        "module__head_dropout_rate": 0.55,
        "train_split": null
    },
    "training_history": [
        {
            "epoch": 1,
            "train_batch_count": 102,
            "valid_batch_count": 26,
            "dur": 62.443897008895874,
            "train_loss": 2.4014250111125626,
            "train_loss_best": true,
            "valid_loss": 2.2332445386000876,
            "valid_loss_best": true,
            "valid_acc": 0.26535626535626533,
            "valid_acc_best": true,
            "event_lr": 1e-05,
            "train_acc": 0.1505838967424708,
            "train_acc_best": true
        },
        {
            "epoch": 2,
            "train_batch_count": 102,
            "valid_batch_count": 26,
            "dur": 58.973429441452026,
            "train_loss": 2.1779730882685686,
            "train_loss_best": true,
            "valid_loss": 2.035426290380867,
            "valid_loss_best": true,
            "valid_acc": 0.3538083538083538,
            "valid_acc_best": true,
            "event_lr": 9.995015679379509e-06,
            "train_acc": 0.2538414259373079,
            "train_acc_best": true
        },
        {
            "epoch": 3,
            "train_batch_count": 102,
            "valid_batch_count": 26,
            "dur": 58.30473732948303,
            "train_loss": 1.9797063717170955,
            "train_loss_best": true,
            "valid_loss": 1.8645606538880368,
            "valid_loss_best": true,
            "valid_acc": 0.3808353808353808,
            "valid_acc_best": true,
            "event_lr": 9.980072755276436e-06,
            "train_acc": 0.33743085433312847,
            "train_acc_best": true
        },
        {
            "epoch": 4,
            "train_batch_count": 102,
            "valid_batch_count": 26,
            "dur": 58.15619921684265,
            "train_loss": 1.8090241645550391,
            "train_loss_best": true,
            "valid_loss": 1.7639178005424705,
            "valid_loss_best": true,
            "valid_acc": 0.4152334152334152,
            "valid_acc_best": true,
            "event_lr": 9.955201320751279e-06,
            "train_acc": 0.38229870928088505,
            "train_acc_best": true
        },
        {
            "epoch": 5,
            "train_batch_count": 102,
            "valid_batch_count": 26,
            "dur": 57.99102163314819,
            "train_loss": 1.681449429345556,
            "train_loss_best": true,
            "valid_loss": 1.6971198370181373,
            "valid_loss_best": true,
            "valid_acc": 0.43243243243243246,
            "valid_acc_best": true,
            "event_lr": 9.92045146356322e-06,
            "train_acc": 0.43146896127842654,
            "train_acc_best": true
        },
        {
            "epoch": 6,
            "train_batch_count": 102,
            "valid_batch_count": 26,
            "dur": 57.93809509277344,
            "train_loss": 1.5812585385357154,
            "train_loss_best": true,
            "valid_loss": 1.6428877777198023,
            "valid_loss_best": true,
            "valid_acc": 0.4594594594594595,
            "valid_acc_best": true,
            "event_lr": 9.875893165300029e-06,
            "train_acc": 0.46465888137676703,
            "train_acc_best": true
        },
        {
            "epoch": 7,
            "train_batch_count": 102,
            "valid_batch_count": 26,
            "dur": 57.87074637413025,
            "train_loss": 1.5062496671664913,
            "train_loss_best": true,
            "valid_loss": 1.6022360078825704,
            "valid_loss_best": true,
            "valid_acc": 0.44717444717444715,
            "valid_acc_best": false,
            "event_lr": 9.821616160444476e-06,
            "train_acc": 0.5046097111247695,
            "train_acc_best": true
        },
        {
            "epoch": 8,
            "train_batch_count": 102,
            "valid_batch_count": 26,
            "dur": 57.8878128528595,
            "train_loss": 1.4355942103198942,
            "train_loss_best": true,
            "valid_loss": 1.5785314011632372,
            "valid_loss_best": true,
            "valid_acc": 0.4643734643734644,
            "valid_acc_best": true,
            "event_lr": 9.757729755661012e-06,
            "train_acc": 0.5046097111247695,
            "train_acc_best": false
        },
        {
            "epoch": 9,
            "train_batch_count": 102,
            "valid_batch_count": 26,
            "dur": 57.97803783416748,
            "train_loss": 1.3670513284814527,
            "train_loss_best": true,
            "valid_loss": 1.5483152470951878,
            "valid_loss_best": true,
            "valid_acc": 0.4619164619164619,
            "valid_acc_best": false,
            "event_lr": 9.684362609666702e-06,
            "train_acc": 0.5334972341733252,
            "train_acc_best": true
        },
        {
            "epoch": 10,
            "train_batch_count": 102,
            "valid_batch_count": 26,
            "dur": 58.04220652580261,
            "train_loss": 1.317231298079136,
            "train_loss_best": true,
            "valid_loss": 1.5402759460032132,
            "valid_loss_best": true,
            "valid_acc": 0.4668304668304668,
            "valid_acc_best": true,
            "event_lr": 9.601662474129683e-06,
            "train_acc": 0.5507068223724647,
            "train_acc_best": true
        },
        {
            "epoch": 11,
            "train_batch_count": 102,
            "valid_batch_count": 26,
            "dur": 57.95815873146057,
            "train_loss": 1.2397063053233095,
            "train_loss_best": true,
            "valid_loss": 1.5258601473356055,
            "valid_loss_best": true,
            "valid_acc": 0.457002457002457,
            "valid_acc_best": false,
            "event_lr": 9.509795896116976e-06,
            "train_acc": 0.5820528580208973,
            "train_acc_best": true
        },
        {
            "epoch": 12,
            "train_batch_count": 102,
            "valid_batch_count": 26,
            "dur": 57.96004843711853,
            "train_loss": 1.214312149911258,
            "train_loss_best": true,
            "valid_loss": 1.516992701652302,
            "valid_loss_best": true,
            "valid_acc": 0.4619164619164619,
            "valid_acc_best": false,
            "event_lr": 9.408947882690855e-06,
            "train_acc": 0.5857406269207129,
            "train_acc_best": true
        },
        {
            "epoch": 13,
            "train_batch_count": 102,
            "valid_batch_count": 26,
            "dur": 57.83709645271301,
            "train_loss": 1.1804570009463684,
            "train_loss_best": true,
            "valid_loss": 1.5163731733176866,
            "valid_loss_best": true,
            "valid_acc": 0.48402948402948404,
            "valid_acc_best": true,
            "event_lr": 9.299321528329239e-06,
            "train_acc": 0.6004917025199754,
            "train_acc_best": true
        },
        {
            "epoch": 14,
            "train_batch_count": 102,
            "valid_batch_count": 26,
            "dur": 58.960872411727905,
            "train_loss": 1.13537965490544,
            "train_loss_best": true,
            "valid_loss": 1.5069011769072136,
            "valid_loss_best": true,
            "valid_acc": 0.48402948402948404,
            "valid_acc_best": false,
            "event_lr": 9.18113760592045e-06,
            "train_acc": 0.6213890596189305,
            "train_acc_best": true
        },
        {
            "epoch": 15,
            "train_batch_count": 102,
            "valid_batch_count": 26,
            "dur": 70.6437623500824,
            "train_loss": 1.0854982139878135,
            "train_loss_best": true,
            "valid_loss": 1.5111283564743305,
            "valid_loss_best": false,
            "valid_acc": 0.4742014742014742,
            "valid_acc_best": false,
            "event_lr": 9.054634122155993e-06,
            "train_acc": 0.6422864167178857,
            "train_acc_best": true
        },
        {
            "epoch": 16,
            "train_batch_count": 102,
            "valid_batch_count": 26,
            "dur": 59.13971185684204,
            "train_loss": 1.056077710418666,
            "train_loss_best": true,
            "valid_loss": 1.4906160351099487,
            "valid_loss_best": true,
            "valid_acc": 0.49385749385749383,
            "valid_acc_best": true,
            "event_lr": 8.920065838216751e-06,
            "train_acc": 0.6515058389674248,
            "train_acc_best": true
        },
        {
            "epoch": 17,
            "train_batch_count": 102,
            "valid_batch_count": 26,
            "dur": 58.781593322753906,
            "train_loss": 1.010235756690618,
            "train_loss_best": true,
            "valid_loss": 1.5149997373177906,
            "valid_loss_best": false,
            "valid_acc": 0.4692874692874693,
            "valid_acc_best": false,
            "event_lr": 8.777703756717879e-06,
            "train_acc": 0.6644130301167793,
            "train_acc_best": true
        },
        {
            "epoch": 18,
            "train_batch_count": 102,
            "valid_batch_count": 26,
            "dur": 58.04903984069824,
            "train_loss": 0.9778760733161884,
            "train_loss_best": true,
            "valid_loss": 1.4881882222337277,
            "valid_loss_best": true,
            "valid_acc": 0.4864864864864865,
            "valid_acc_best": false,
            "event_lr": 8.627834575945592e-06,
            "train_acc": 0.6803933620159803,
            "train_acc_best": true
        },
        {
            "epoch": 19,
            "train_batch_count": 102,
            "valid_batch_count": 26,
            "dur": 57.536423683166504,
            "train_loss": 0.9259313782740021,
            "train_loss_best": true,
            "valid_loss": 1.4962154541906034,
            "valid_loss_best": false,
            "valid_acc": 0.49385749385749383,
            "valid_acc_best": false,
            "event_lr": 8.470760112484985e-06,
            "train_acc": 0.6926859250153657,
            "train_acc_best": true
        },
        {
            "epoch": 20,
            "train_batch_count": 102,
            "valid_batch_count": 26,
            "dur": 58.94031023979187,
            "train_loss": 0.9110760146954635,
            "train_loss_best": true,
            "valid_loss": 1.508552633866631,
            "valid_loss_best": false,
            "valid_acc": 0.4742014742014742,
            "valid_acc_best": false,
            "event_lr": 8.306796693401581e-06,
            "train_acc": 0.7098955132145052,
            "train_acc_best": true
        },
        {
            "epoch": 21,
            "train_batch_count": 102,
            "valid_batch_count": 26,
            "dur": 58.737807750701904,
            "train_loss": 0.8593320365177757,
            "train_loss_best": true,
            "valid_loss": 1.5118683725961597,
            "valid_loss_best": false,
            "valid_acc": 0.47911547911547914,
            "valid_acc_best": false,
            "event_lr": 8.136274519200735e-06,
            "train_acc": 0.7228027043638598,
            "train_acc_best": true
        },
        {
            "epoch": 22,
            "train_batch_count": 102,
            "valid_batch_count": 26,
            "dur": 58.72734355926514,
            "train_loss": 0.8400241091307058,
            "train_loss_best": true,
            "valid_loss": 1.5506370178897493,
            "valid_loss_best": false,
            "valid_acc": 0.4643734643734644,
            "valid_acc_best": false,
            "event_lr": 7.959536998847746e-06,
            "train_acc": 0.734480639213276,
            "train_acc_best": true
        },
        {
            "epoch": 23,
            "train_batch_count": 102,
            "valid_batch_count": 26,
            "dur": 59.27450346946716,
            "train_loss": 0.8219428790736653,
            "train_loss_best": true,
            "valid_loss": 1.5110571466441236,
            "valid_loss_best": false,
            "valid_acc": 0.4987714987714988,
            "valid_acc_best": true,
            "event_lr": 7.77694005818791e-06,
            "train_acc": 0.7338660110633067,
            "train_acc_best": false
        },
        {
            "epoch": 24,
            "train_batch_count": 102,
            "valid_batch_count": 26,
            "dur": 59.6176643371582,
            "train_loss": 0.7939206967708444,
            "train_loss_best": true,
            "valid_loss": 1.5254593903075273,
            "valid_loss_best": false,
            "valid_acc": 0.4914004914004914,
            "valid_acc_best": false,
            "event_lr": 7.588851423159238e-06,
            "train_acc": 0.7363245236631838,
            "train_acc_best": true
        },
        {
            "epoch": 25,
            "train_batch_count": 102,
            "valid_batch_count": 26,
            "dur": 58.874473571777344,
            "train_loss": 0.7724377689511042,
            "train_loss_best": true,
            "valid_loss": 1.5477536556468843,
            "valid_loss_best": false,
            "valid_acc": 0.4594594594594595,
            "valid_acc_best": false,
            "event_lr": 7.395649879241345e-06,
            "train_acc": 0.7541487400122926,
            "train_acc_best": true
        },
        {
            "epoch": 26,
            "train_batch_count": 102,
            "valid_batch_count": 26,
            "dur": 59.34532141685486,
            "train_loss": 0.723566580602708,
            "train_loss_best": true,
            "valid_loss": 1.5577838174834004,
            "valid_loss_best": false,
            "valid_acc": 0.47665847665847666,
            "valid_acc_best": false,
            "event_lr": 7.197724508631914e-06,
            "train_acc": 0.7738168408113092,
            "train_acc_best": true
        },
        {
            "epoch": 27,
            "train_batch_count": 102,
            "valid_batch_count": 26,
            "dur": 58.58491563796997,
            "train_loss": 0.7017582559336455,
            "train_loss_best": true,
            "valid_loss": 1.5456999578405657,
            "valid_loss_best": false,
            "valid_acc": 0.48157248157248156,
            "valid_acc_best": false,
            "event_lr": 6.995473906686924e-06,
            "train_acc": 0.7854947756607252,
            "train_acc_best": true
        },
        {
            "epoch": 28,
            "train_batch_count": 102,
            "valid_batch_count": 26,
            "dur": 57.91788625717163,
            "train_loss": 0.6973920009512805,
            "train_loss_best": true,
            "valid_loss": 1.5501478145983647,
            "valid_loss_best": false,
            "valid_acc": 0.48894348894348894,
            "valid_acc_best": false
        }
    ]
}