{
    "image_id": "Brasov_21-05-2025_square",
    "prediction_id": "p4",
    "experiment_run_id_of_model": "20250612_234618_seed42",
    "image_user_source_path": "images/eugen/Brasov_21-05-2025_square.jpg",
    "probabilities": [
        0.11469835788011551,
        0.014059353619813919,
        0.4962857663631439,
        0.0011033499613404274,
        0.005236807744950056,
        0.0009230948053300381,
        0.36769330501556396
    ],
    "predicted_class_idx": 2,
    "predicted_class_name": "3_cirrus",
    "confidence": 0.4962857663631439,
    "top_k_predictions_for_plot": [
        [
            "3_cirrus",
            0.4962857663631439
        ],
        [
            "7_mixed",
            0.36769330501556396
        ],
        [
            "1_cumulus",
            0.11469835788011551
        ],
        [
            "2_altocumulus",
            0.014059353619813919
        ],
        [
            "5_stratocumulus",
            0.005236807744950056
        ],
        [
            "4_clearsky",
            0.0011033499613404274
        ],
        [
            "6_cumulonimbus",
            0.0009230948053300381
        ]
    ],
    "lime_explanation": {
        "explained_class_idx": 2,
        "explained_class_name": "3_cirrus",
        "feature_weights": [
            [
                72,
                0.021844350073476387
            ],
            [
                26,
                0.020330625664073038
            ],
            [
                73,
                0.018038667753848412
            ],
            [
                2,
                0.017570074736236972
            ],
            [
                71,
                0.017384394456086093
            ],
            [
                20,
                0.017257146233461598
            ],
            [
                47,
                0.017235514322518873
            ],
            [
                4,
                0.015882217730798318
            ],
            [
                18,
                0.015213280522250974
            ],
            [
                78,
                0.015066136827971614
            ],
            [
                62,
                0.013789121517639703
            ],
            [
                61,
                0.013629584747562302
            ],
            [
                6,
                0.013168515291795344
            ],
            [
                106,
                0.013011054120121617
            ],
            [
                37,
                0.012154614224497236
            ],
            [
                5,
                0.011611993837206432
            ],
            [
                66,
                0.011256846757074104
            ],
            [
                99,
                0.009907082081493207
            ],
            [
                44,
                0.009211668096484105
            ],
            [
                9,
                0.0057895473216865445
            ]
        ],
        "num_features_from_lime_run": 20
    }
}